blackspace-0.0.55.dist-info/licenses/LICENSE
blackspace_compiler/__init__.py
blackspace_compiler/__main__.py
blackspace_compiler/ast/__init__.py
blackspace_compiler/ast/debugstatement.py
blackspace_compiler/ast/node.py
blackspace_compiler/ast/context/__init__.py
blackspace_compiler/ast/context/compileconfig.py
blackspace_compiler/ast/context/evaluation_context.py
blackspace_compiler/ast/context/function_registry.py
blackspace_compiler/ast/context/issue_level.py
blackspace_compiler/ast/context/label_registry.py
blackspace_compiler/ast/context/heap/__init__.py
blackspace_compiler/ast/context/heap/helpers.py
blackspace_compiler/ast/context/stack/__init__.py
blackspace_compiler/ast/context/stack/helpers.py
blackspace_compiler/ast/definitions/__init__.py
blackspace_compiler/ast/definitions/function.py
blackspace_compiler/ast/definitions/variable.py
blackspace_compiler/ast/expressions/__init__.py
blackspace_compiler/ast/expressions/expression.py
blackspace_compiler/ast/expressions/builtinfunctions/__init__.py
blackspace_compiler/ast/expressions/builtinfunctions/sizeof.py
blackspace_compiler/ast/expressions/functions/__init__.py
blackspace_compiler/ast/expressions/functions/function_call.py
blackspace_compiler/ast/expressions/literals/__init__.py
blackspace_compiler/ast/expressions/literals/array.py
blackspace_compiler/ast/expressions/literals/bool.py
blackspace_compiler/ast/expressions/literals/int.py
blackspace_compiler/ast/expressions/literals/string.py
blackspace_compiler/ast/expressions/operations/__init__.py
blackspace_compiler/ast/expressions/operations/arithmetic.py
blackspace_compiler/ast/expressions/operations/boolean.py
blackspace_compiler/ast/expressions/operations/comparison.py
blackspace_compiler/ast/expressions/operations/operator.py
blackspace_compiler/ast/expressions/variables/__init__.py
blackspace_compiler/ast/expressions/variables/array_index.py
blackspace_compiler/ast/expressions/variables/memory_fetch.py
blackspace_compiler/ast/expressions/variables/variable_access.py
blackspace-0.0.55.dist-info/METADATA
blackspace-0.0.55.dist-info/WHEEL
blackspace-0.0.55.dist-info/entry_points.txt
blackspace-0.0.55.dist-info/top_level.txt
blackspace-0.0.55.dist-info/RECORD
