Metadata-Version: 2.4
Name: blackspace
Version: 0.0.55
Summary: BlackSpace is a programming language that compiles to WhiteSpace.
Author: Bence Skorka
License-Expression: MIT
Classifier: Development Status :: 2 - Pre-Alpha
Classifier: Environment :: Console
Requires-Python: >=3.12
License-File: LICENSE
Provides-Extra: build
Requires-Dist: pip-tools; extra == "build"
Requires-Dist: setuptools; extra == "build"
Requires-Dist: twine; extra == "build"
Provides-Extra: publish
Requires-Dist: twine; extra == "publish"
Provides-Extra: types
Requires-Dist: types-mock; extra == "types"
Provides-Extra: test
Requires-Dist: black; extra == "test"
Requires-Dist: mock; extra == "test"
Requires-Dist: mypy; extra == "test"
Requires-Dist: pytest-cov; extra == "test"
Requires-Dist: pytest-mock; extra == "test"
Requires-Dist: pytest-mypy; extra == "test"
Requires-Dist: pytest-timeout; extra == "test"
Requires-Dist: pytest; extra == "test"
Provides-Extra: dotenv
Requires-Dist: python-dotenv; extra == "dotenv"
Dynamic: license-file
